mlsort/__init__.py
mlsort/algorithms.py
mlsort/api.py
mlsort/baseline.py
mlsort/benchmark.py
mlsort/cli_bench_compare.py
mlsort/cli_bench_install.py
mlsort/cli_init.py
mlsort/cli_optimize_cutoffs.py
mlsort/config.py
mlsort/data.py
mlsort/decision.py
mlsort/features.py
mlsort/installer.py
mlsort/model.py
mlsort/optimize.py
mlsort-0.1.0.dist-info/licenses/LICENSE
mlsort-0.1.0.dist-info/METADATA
mlsort-0.1.0.dist-info/WHEEL
mlsort-0.1.0.dist-info/entry_points.txt
mlsort-0.1.0.dist-info/top_level.txt
mlsort-0.1.0.dist-info/RECORD
