Metadata-Version: 2.4
Name: mlsort
Version: 0.1.0
Summary: ML-guided sorting backend selector with install-time benchmarking
Author: Siddharth Chaudhary
License: MIT License
Project-URL: Homepage, https://github.com/sidcoding/mlsort
Project-URL: Repository, https://github.com/sidcoding/mlsort
Project-URL: Issues, https://github.com/sidcoding/mlsort/issues
Keywords: sorting,machine-learning,numpy,performance,benchmark,timsort,radix,counting-sort,decision-tree
Classifier: Programming Language :: Python :: 3
Classifier: Programming Language :: Python :: 3 :: Only
Classifier: Programming Language :: Python :: 3.9
Classifier: Programming Language :: Python :: 3.10
Classifier: Programming Language :: Python :: 3.11
Classifier: License :: OSI Approved :: MIT License
Classifier: Operating System :: OS Independent
Classifier: Intended Audience :: Developers
Classifier: Topic :: Software Development :: Libraries
Classifier: Topic :: System :: Benchmark
Requires-Python: >=3.9
License-File: LICENSE
Requires-Dist: numpy>=1.24
Requires-Dist: scikit-learn>=1.3
Requires-Dist: scipy>=1.10
Requires-Dist: joblib>=1.3
Dynamic: license-file
